rtl/slave.v
module slave #(
    parameter ADDR_WD = 32,
    parameter DATA_WD = 32,
    parameter STRB_WD = 4,
    parameter PROT_WD = 3
)(
    input                  b_pclk,
    input                  b_prst_n,

    input                  b_psel,
    input                  b_penable,
    input                  b_pwrite,
    input  [ADDR_WD-1 : 0] b_paddr,
    input  [DATA_WD-1 : 0] b_pwdata,
    input  [PROT_WD-1 : 0] b_pprot,
    input  [STRB_WD-1 : 0] b_pstrb,
    output [DATA_WD-1 : 0] b_prdata,
    output                 b_pready                
);

localparam ADDR_WD_L = ADDR_WD - 2;

reg [DATA_WD-1 : 0] mem [(1 << ADDR_WD_L)-1 : 0];

wire [ADDR_WD_L-1 : 0] b_paddr_L;

assign b_paddr_L = b_paddr[ADDR_WD_L-1 : 0];
assign b_pready = 1;

always @(posedge b_pclk or negedge b_prst_n ) begin
    if (b_penable && b_pwrite && b_pready) begin
        mem[b_paddr_L] <= b_pwdata;
    end
end

assign b_prdata = mem[b_paddr_L];

endmodule

rtl/slave_mux.v
module slave_mux #(
    parameter ADDR_WD = 32,
    parameter DATA_WD = 32,
    parameter STRB_WD = 4,
    parameter PROT_WD = 3
)(
    input                  b_pclk,
    input                  b_prst_n,

    input                  b_psel,
    input                  b_penable,
    input                  b_pwrite,
    input  [ADDR_WD-1 : 0] b_paddr,
    input  [DATA_WD-1 : 0] b_pwdata,
    input  [PROT_WD-1 : 0] b_pprot,
    input  [STRB_WD-1 : 0] b_pstrb,
    output [DATA_WD-1 : 0] b_prdata,
    output                 b_pready                
);

wire [DATA_WD-1 : 0] prdata0, prdata1, prdata2, prdata3;
wire                 psel0,   psel1,   psel2,   psel3;
wire                 pready0, pready1, pready2, pready3;

wire [1 : 0] addrx;
wire [3 : 0] selx;

reg [DATA_WD-1 : 0] b_prdata_r;

assign b_prdata = b_prdata_r;

assign addrx = b_paddr[ADDR_WD-1 : ADDR_WD-2];
assign selx  = {addrx == 2'd3, addrx == 2'd2, addrx == 2'd1, addrx == 2'd0};
assign psel0 = b_psel && selx[0];
assign psel1 = b_psel && selx[1];
assign psel2 = b_psel && selx[2];
assign psel3 = b_psel && selx[3];

assign b_pready = pready0 && selx[0] || pready1 && selx[1] || pready2 && selx[2] || pready2 && selx[3]; 

always @(*) begin
    case (selx)
        4'b0001: b_prdata_r = prdata0;
        4'b0010: b_prdata_r = prdata1;
        4'b0100: b_prdata_r = prdata2;
        4'b1000: b_prdata_r = prdata3;
        default: b_prdata_r = prdata0;
    endcase
end

slave #(
    .ADDR_WD(ADDR_WD),
    .DATA_WD(DATA_WD),
    .STRB_WD(STRB_WD),
    .PROT_WD(PROT_WD)
)  slave0(
    .b_pclk(b_pclk),
    .b_prst_n(b_prst_n),
    .b_psel(psel0),
    .b_penable(b_penable),
    .b_pwrite(b_pwrite),
    .b_paddr(b_paddr),
    .b_pwdata(b_pwdata),
    .b_pprot(b_pprot),
    .b_pstrb(b_pstrb),
    .b_prdata(prdata0),
    .b_pready(pready0)
);

slave #(
    .ADDR_WD(ADDR_WD),
    .DATA_WD(DATA_WD),
    .STRB_WD(STRB_WD),
    .PROT_WD(PROT_WD)
)  slave1(
    .b_pclk(b_pclk),
    .b_prst_n(b_prst_n),
    .b_psel(psel1),
    .b_penable(b_penable),
    .b_pwrite(b_pwrite),
    .b_paddr(b_paddr),
    .b_pwdata(b_pwdata),
    .b_pprot(b_pprot),
    .b_pstrb(b_pstrb),
    .b_prdata(prdata1),
    .b_pready(pready1)
);

slave #(
    .ADDR_WD(ADDR_WD),
    .DATA_WD(DATA_WD),
    .STRB_WD(STRB_WD),
    .PROT_WD(PROT_WD)
)  slave2(
    .b_pclk(b_pclk),
    .b_prst_n(b_prst_n),
    .b_psel(psel2),
    .b_penable(b_penable),
    .b_pwrite(b_pwrite),
    .b_paddr(b_paddr),
    .b_pwdata(b_pwdata),
    .b_pprot(b_pprot),
    .b_pstrb(b_pstrb),
    .b_prdata(prdata2),
    .b_pready(pready2)
);

slave #(
    .ADDR_WD(ADDR_WD),
    .DATA_WD(DATA_WD),
    .STRB_WD(STRB_WD),
    .PROT_WD(PROT_WD)
)  slave3(
    .b_pclk(b_pclk),
    .b_prst_n(b_prst_n),
    .b_psel(psel3),
    .b_penable(b_penable),
    .b_pwrite(b_pwrite),
    .b_paddr(b_paddr),
    .b_pwdata(b_pwdata),
    .b_pprot(b_pprot),
    .b_pstrb(b_pstrb),
    .b_prdata(prdata3),
    .b_pready(pready3)
);

endmodule

rtl/low_frequency_apb.v
module low_frequency_apb #(
    parameter ADDR_WD = 32,
    parameter DATA_WD = 32,
    parameter STRB_WD = 4,
    parameter PROT_WD = 3
)(
    input                  b_pclk,
    input                  b_prst_n,

    output                 b_psel,
    output                 b_penable,
    output                 b_pwrite,
    output [ADDR_WD-1 : 0] b_paddr,
    output [DATA_WD-1 : 0] b_pwdata,
    output [PROT_WD-1 : 0] b_pprot,
    output [STRB_WD-1 : 0] b_pstrb,
    input  [DATA_WD-1 : 0] b_prdata,
    input                  b_pready,

    input                  a_apb_req,
    input                  write,
    input  [ADDR_WD-1 : 0] addr,
    input  [DATA_WD-1 : 0] wdata,
    input  [PROT_WD-1 : 0] prot,
    input  [STRB_WD-1 : 0] strb,

    output                 b_ready_req,
    output [DATA_WD-1 : 0] rdata                   
);

reg b_psel_r;
reg b_penable_r;
reg b_ready_req_r;

reg                 b_pwrite_r;
reg [ADDR_WD-1 : 0] b_paddr_r;
reg [DATA_WD-1 : 0] b_pwdata_r;
reg [PROT_WD-1 : 0] b_pprot_r;
reg [STRB_WD-1 : 0] b_pstrb_r;

reg [DATA_WD-1 : 0] rdata_r;

reg q1_r, q2_r, q3_r;

wire a2b_apb_req_edge;

// generate pulse
always @(posedge b_pclk or negedge b_prst_n) begin
    if (!b_prst_n) begin
        {q1_r, q2_r, q3_r} <= 'b0;
    end
    else begin
        {q1_r, q2_r, q3_r} <= {a_apb_req, q1_r, q2_r};
    end
end

assign a2b_apb_req_edge = q2_r ^ q3_r;

//  control path
always @(posedge b_pclk or negedge b_prst_n) begin
    if (!b_prst_n) begin
        b_psel_r <= 1'b0;
    end
    else begin 
        if (a2b_apb_req_edge) begin
            b_psel_r <= 1'b1;
        end     
        else if (b_penable && b_pready) begin
            b_psel_r <= 1'b0;
        end
    end
end

always @(posedge b_pclk or negedge b_prst_n) begin
    if (!b_prst_n) begin
        b_penable_r   <= 1'b0;
        b_ready_req_r <= 1'b0;
    end
    else begin
        if (b_psel) begin
            b_penable_r <= 1'b1;
        end
        if (b_penable && b_pready) begin
            b_penable_r   <= 1'b0;
            b_ready_req_r <= ~b_ready_req_r;
        end
    end
end

always @(posedge b_pclk) begin
    if (a2b_apb_req_edge) begin
        b_pwrite_r <= write;
        b_pwdata_r <= wdata;
        b_paddr_r  <= addr;
        b_pprot_r  <= prot;
        b_pstrb_r  <= strb;
    end
end

always @(posedge b_pclk or negedge b_prst_n) begin
    if (!b_pwrite && b_psel) begin
        rdata_r <= b_prdata;
    end
end

assign b_psel      = b_psel_r;
assign b_penable   = b_penable_r;
assign b_ready_req = b_ready_req_r;
assign b_pwrite    = b_pwrite_r;
assign b_pwdata    = b_pwdata_r;
assign b_paddr     = b_paddr_r;
assign b_pprot     = b_pprot_r;
assign b_pstrb     = b_pstrb_r;
assign rdata       = rdata_r;

endmodule

rtl/high_frequency_apb.v
module high_frequency_apb #(
    parameter ADDR_WD = 32,
    parameter DATA_WD = 32,
    parameter STRB_WD = 4,
    parameter PROT_WD = 3
)(
    input                  a_pclk,
    input                  a_prst_n,

    input                  a_psel,
    input                  a_penable,
    input                  a_pwrite,
    input  [ADDR_WD-1 : 0] a_paddr,
    input  [DATA_WD-1 : 0] a_pwdata,
    input  [PROT_WD-1 : 0] a_pprot,
    input  [STRB_WD-1 : 0] a_pstrb,
    output [DATA_WD-1 : 0] a_prdata,
    output                 a_pready,

    output                 a_apb_req,
    output                 write,
    output [ADDR_WD-1 : 0] addr,
    output [DATA_WD-1 : 0] wdata,
    output [PROT_WD-1 : 0] prot,
    output [STRB_WD-1 : 0] strb,

    input                  b_ready_req,
    input  [DATA_WD-1 : 0] rdata                   
);

reg                 a_pwrite_r;
reg [ADDR_WD-1 : 0] a_paddr_r;
reg [DATA_WD-1 : 0] a_pwdata_r;
reg [PROT_WD-1 : 0] a_pprot_r;
reg [STRB_WD-1 : 0] a_pstrb_r;
reg [DATA_WD-1 : 0] a_prdata_r;
reg                 a_pready_r;
reg                 a_apb_req_r;

wire b2a_ready_req_edge;

reg q1_r, q2_r, q3_r;

// generate pulse
always @(posedge a_pclk or negedge a_prst_n) begin
    if (!a_prst_n) begin
        {q1_r, q2_r, q3_r} <= 'b0;
    end
    else begin
        {q1_r, q2_r, q3_r} <= {b_ready_req, q1_r, q2_r};
    end
end

assign b2a_ready_req_edge = q2_r ^ q3_r;

always @(posedge a_pclk or negedge a_prst_n) begin
    if (!a_prst_n) begin
        a_apb_req_r <= 1'b0;
    end
    else if (a_psel && !a_penable) begin
        a_apb_req_r <= !a_apb_req_r;
        a_pwrite_r  <= a_pwrite;
        a_pwdata_r  <= a_pwdata;
        a_paddr_r   <= a_paddr;
        a_pprot_r   <= a_pprot;
        a_pstrb_r   <= a_pstrb;
    end    
end

always @(posedge a_pclk or negedge a_prst_n) begin
    if (!a_prst_n) begin
        a_pready_r <= 1'b1;
    end
    else begin
        if (a_psel && !a_penable) begin
            a_pready_r <= 1'b0;
        end
        else if (b2a_ready_req_edge) begin
            a_pready_r <= 1'b1;
            a_prdata_r <= rdata;
        end
    end
end

assign a_apb_req = a_apb_req_r;
assign write     = a_pwrite_r;
assign addr      = a_paddr_r;
assign wdata     = a_pwdata_r;
assign prot      = a_pprot_r;
assign strb      = a_pstrb;
assign a_pready  = a_pready_r;
assign a_prdata  = a_prdata_r;

endmodule

rtl/asyn_bridge_top.v
module asyn_bridge_top #(
    parameter ADDR_WD = 32,
    parameter DATA_WD = 32,
    parameter STRB_WD = 4,
    parameter PROT_WD = 3
)(
    input                  a_pclk,
    input                  a_prst_n,

    input                  a_psel,
    input                  a_penable,
    input                  a_pwrite,
    input  [ADDR_WD-1 : 0] a_paddr,
    input  [DATA_WD-1 : 0] a_pwdata,
    input  [PROT_WD-1 : 0] a_pprot,
    input  [STRB_WD-1 : 0] a_pstrb,
    output [DATA_WD-1 : 0] a_prdata,
    output                 a_pready,

    input                  b_pclk,
    input                  b_prst_n,

    output                 b_psel,
    output                 b_penable,
    output                 b_pwrite,
    output [ADDR_WD-1 : 0] b_paddr,
    output [DATA_WD-1 : 0] b_pwdata,
    output [PROT_WD-1 : 0] b_pprot,
    output [STRB_WD-1 : 0] b_pstrb,
    input  [DATA_WD-1 : 0] b_prdata,
    input                  b_pready                   
);

wire                 a_apb_req;
wire                 write;
wire [ADDR_WD-1 : 0] addr;
wire [DATA_WD-1 : 0] wdata;
wire [PROT_WD-1 : 0] prot;
wire [STRB_WD-1 : 0] strb;
wire                 b_ready_req;
wire [DATA_WD-1 : 0] rdata;

high_frequency_apb #(
    .ADDR_WD(ADDR_WD),
    .DATA_WD(DATA_WD),
    .STRB_WD(STRB_WD),
    .PROT_WD(PROT_WD)
)  high_frequency(
    .a_pclk(a_pclk),
    .a_prst_n(a_prst_n),
    .a_psel(a_psel),
    .a_penable(a_penable),
    .a_pwrite(a_pwrite),
    .a_paddr(a_paddr),
    .a_pwdata(a_pwdata),
    .a_pprot(a_pprot),
    .a_pstrb(a_pstrb),
    .a_prdata(a_prdata),
    .a_pready(a_pready),
    .a_apb_req(a_apb_req),
    .write(write),
    .addr(addr),
    .wdata(wdata),
    .prot(prot),
    .strb(strb),
    .b_ready_req(b_ready_req),
    .rdata(rdata)
);

low_frequency_apb #(
    .ADDR_WD(ADDR_WD),
    .DATA_WD(DATA_WD),
    .STRB_WD(STRB_WD),
    .PROT_WD(PROT_WD)
) low_frequency(
    .b_pclk(b_pclk),
    .b_prst_n(b_prst_n),
    .b_psel(b_psel),
    .b_penable(b_penable),
    .b_pwrite(b_pwrite),
    .b_paddr(b_paddr),
    .b_pwdata(b_pwdata),
    .b_pprot(b_pprot),
    .b_pstrb(b_pstrb),
    .b_prdata(b_prdata),
    .b_pready(b_pready),
    .a_apb_req(a_apb_req),
    .write(write),
    .addr(addr),
    .wdata(wdata),
    .prot(prot),
    .strb(strb),
    .b_ready_req(b_ready_req),
    .rdata(rdata)
);
    
endmodule

sim/tb_asyn_bridge.v
`timescale 1ns / 1ns
module tb_asyn_bridge;

localparam ADDR_WD = 8,
           DATA_WD = 6,
           STRB_WD = 2,
           PROT_WD = 4;

reg                  a_pclk;
reg                  a_prst_n;
reg                  b_pclk;
reg                  b_prst_n;
reg                  a_psel;
reg                  a_penable;
reg                  a_pwrite;
reg  [ADDR_WD-1 : 0] a_paddr;
reg  [DATA_WD-1 : 0] a_pwdata;
reg  [PROT_WD-1 : 0] a_pprot;
reg  [STRB_WD-1 : 0] a_pstrb;

wire [DATA_WD-1 : 0] a_prdata;
wire                 a_pready;

wire                 b_psel;
wire                 b_penable;
wire                 b_pwrite;
wire [ADDR_WD-1 : 0] b_paddr;
wire [DATA_WD-1 : 0] b_pwdata;
wire [PROT_WD-1 : 0] b_pprot;
wire [STRB_WD-1 : 0] b_pstrb;
wire [DATA_WD-1 : 0] b_prdata;
wire                 b_pready;

reg  [ADDR_WD-1 : 0] cnt;

initial begin
    $dumpfile("asyn_bridge.vcd");
    $dumpvars;
end

initial begin
    a_pclk = 1'b0;
    forever begin
        #3;
        a_pclk = ~a_pclk;
    end
end

initial begin
    b_pclk = 1'b0;
    forever begin
        #6;
        b_pclk = ~b_pclk;
    end
end

initial begin
    a_prst_n = 1'b1;
    b_prst_n = 1'b1;
    #1;
    a_prst_n = 1'b0;
    b_prst_n = 1'b0;
    #1;
    a_prst_n = 1'b1;
    b_prst_n = 1'b1;
    #100000;
    $finish;
end

always @(posedge a_pclk or negedge a_prst_n) begin
    if (!a_prst_n) begin
        a_psel <= 1'b0;
    end
    else begin
        if (!a_psel) begin
            a_psel <= $random;
        end
        else if (a_penable && a_pready) begin
            a_psel <= $random;
        end
    end
end

always @(posedge a_pclk or negedge a_prst_n) begin
    if (!a_prst_n) begin
        a_penable <= 1'b0;
    end
    else begin
        if (a_psel) begin
            a_penable <= 1'b1;
        end
        if (a_penable && a_pready) begin
            a_penable <= 1'b0;
        end
    end
end

always @(posedge a_pclk or negedge a_prst_n) begin
    if (!a_prst_n) begin
        cnt <= 'b0;
    end
    else if (a_penable && a_pready) begin
        cnt <= cnt + 1'b1;
    end
end

always @(posedge a_pclk or negedge a_prst_n) begin
    if (!a_prst_n) begin
        a_pwrite <= 1'b1;
    end
    else if (cnt == {ADDR_WD{1'b1}}) begin
        a_pwrite <= 1'b0;
    end
end

always @(posedge a_pclk) begin
    a_paddr  <= cnt;
    a_pwdata <= cnt[DATA_WD-1 : 0];
end

initial begin
    a_pprot = 3'b0;
    a_pstrb = 4'b1111;
end

asyn_bridge_top #(
    .ADDR_WD(ADDR_WD),
    .DATA_WD(DATA_WD),
    .STRB_WD(STRB_WD),
    .PROT_WD(PROT_WD)
)  asyn_bridge_top(
    .a_pclk(a_pclk),
    .a_prst_n(a_prst_n),
    .a_psel(a_psel),
    .a_penable(a_penable),
    .a_pwrite(a_pwrite),
    .a_paddr(a_paddr),
    .a_pwdata(a_pwdata),
    .a_pprot(a_pprot),
    .a_pstrb(a_pstrb),
    .a_prdata(a_prdata),
    .a_pready(a_pready),
    .b_pclk(b_pclk),
    .b_prst_n(b_prst_n),
    .b_psel(b_psel),
    .b_penable(b_penable),
    .b_pwrite(b_pwrite),
    .b_paddr(b_paddr),
    .b_pwdata(b_pwdata),
    .b_pprot(b_pprot),
    .b_pstrb(b_pstrb),
    .b_prdata(b_prdata),
    .b_pready(b_pready)
);

slave_mux #(
    .ADDR_WD(ADDR_WD),
    .DATA_WD(DATA_WD),
    .STRB_WD(STRB_WD),
    .PROT_WD(PROT_WD)
)  slave_mux(
    .b_pclk(b_pclk),
    .b_prst_n(b_prst_n),
    .b_psel(b_psel),
    .b_penable(b_penable),
    .b_pwrite(b_pwrite),
    .b_paddr(b_paddr),
    .b_pwdata(b_pwdata),
    .b_pprot(b_pprot),
    .b_pstrb(b_pstrb),
    .b_prdata(b_prdata),
    .b_pready(b_pready)
);

endmodule

build/asyn_bridge.vcd
$date
	Fri Nov 18 11:01:46 2022
$end
$version
	Icarus Verilog
$end
$timescale
	1ns
$end
$scope module tb_asyn_bridge $end
$var wire 1 ! b_pwrite $end
$var wire 6 " b_pwdata [5:0] $end
$var wire 2 # b_pstrb [1:0] $end
$var wire 1 $ b_psel $end
$var wire 1 % b_pready $end
$var wire 6 & b_prdata [5:0] $end
$var wire 4 ' b_pprot [3:0] $end
$var wire 1 ( b_penable $end
$var wire 8 ) b_paddr [7:0] $end
$var wire 1 * a_pready $end
$var wire 6 + a_prdata [5:0] $end
$var parameter 32 , ADDR_WD $end
$var parameter 32 - DATA_WD $end
$var parameter 32 . PROT_WD $end
$var parameter 32 / STRB_WD $end
$var reg 8 0 a_paddr [7:0] $end
$var reg 1 1 a_pclk $end
$var reg 1 2 a_penable $end
$var reg 4 3 a_pprot [3:0] $end
$var reg 1 4 a_prst_n $end
$var reg 1 5 a_psel $end
$var reg 2 6 a_pstrb [1:0] $end
$var reg 6 7 a_pwdata [5:0] $end
$var reg 1 8 a_pwrite $end
$var reg 1 9 b_pclk $end
$var reg 1 : b_prst_n $end
$var reg 8 ; cnt [7:0] $end
$scope module asyn_bridge_top $end
$var wire 8 < a_paddr [7:0] $end
$var wire 1 1 a_pclk $end
$var wire 1 2 a_penable $end
$var wire 4 = a_pprot [3:0] $end
$var wire 1 4 a_prst_n $end
$var wire 1 5 a_psel $end
$var wire 2 > a_pstrb [1:0] $end
$var wire 6 ? a_pwdata [5:0] $end
$var wire 1 8 a_pwrite $end
$var wire 1 9 b_pclk $end
$var wire 1 : b_prst_n $end
$var wire 1 @ write $end
$var wire 6 A wdata [5:0] $end
$var wire 2 B strb [1:0] $end
$var wire 6 C rdata [5:0] $end
$var wire 4 D prot [3:0] $end
$var wire 1 E b_ready_req $end
$var wire 1 ! b_pwrite $end
$var wire 6 F b_pwdata [5:0] $end
$var wire 2 G b_pstrb [1:0] $end
$var wire 1 $ b_psel $end
$var wire 1 % b_pready $end
$var wire 6 H b_prdata [5:0] $end
$var wire 4 I b_pprot [3:0] $end
$var wire 1 ( b_penable $end
$var wire 8 J b_paddr [7:0] $end
$var wire 8 K addr [7:0] $end
$var wire 1 * a_pready $end
$var wire 6 L a_prdata [5:0] $end
$var wire 1 M a_apb_req $end
$var parameter 32 N ADDR_WD $end
$var parameter 32 O DATA_WD $end
$var parameter 32 P PROT_WD $end
$var parameter 32 Q STRB_WD $end
$scope module high_frequency $end
$var wire 1 M a_apb_req $end
$var wire 8 R a_paddr [7:0] $end
$var wire 1 1 a_pclk $end
$var wire 1 2 a_penable $end
$var wire 4 S a_pprot [3:0] $end
$var wire 6 T a_prdata [5:0] $end
$var wire 1 * a_pready $end
$var wire 1 4 a_prst_n $end
$var wire 1 5 a_psel $end
$var wire 2 U a_pstrb [1:0] $end
$var wire 6 V a_pwdata [5:0] $end
$var wire 1 8 a_pwrite $end
$var wire 8 W addr [7:0] $end
$var wire 1 X b2a_ready_req_edge $end
$var wire 4 Y prot [3:0] $end
$var wire 2 Z strb [1:0] $end
$var wire 6 [ wdata [5:0] $end
$var wire 1 @ write $end
$var wire 6 \ rdata [5:0] $end
$var wire 1 E b_ready_req $end
$var parameter 32 ] ADDR_WD $end
$var parameter 32 ^ DATA_WD $end
$var parameter 32 _ PROT_WD $end
$var parameter 32 ` STRB_WD $end
$var reg 1 a a_apb_req_r $end
$var reg 8 b a_paddr_r [7:0] $end
$var reg 4 c a_pprot_r [3:0] $end
$var reg 6 d a_prdata_r [5:0] $end
$var reg 1 e a_pready_r $end
$var reg 2 f a_pstrb_r [1:0] $end
$var reg 6 g a_pwdata_r [5:0] $end
$var reg 1 h a_pwrite_r $end
$var reg 1 i q1_r $end
$var reg 1 j q2_r $end
$var reg 1 k q3_r $end
$upscope $end
$scope module low_frequency $end
$var wire 1 l a2b_apb_req_edge $end
$var wire 1 M a_apb_req $end
$var wire 8 m addr [7:0] $end
$var wire 1 9 b_pclk $end
$var wire 1 ( b_penable $end
$var wire 4 n b_pprot [3:0] $end
$var wire 1 : b_prst_n $end
$var wire 2 o b_pstrb [1:0] $end
$var wire 6 p b_pwdata [5:0] $end
$var wire 1 ! b_pwrite $end
$var wire 1 E b_ready_req $end
$var wire 4 q prot [3:0] $end
$var wire 6 r rdata [5:0] $end
$var wire 2 s strb [1:0] $end
$var wire 6 t wdata [5:0] $end
$var wire 1 @ write $end
$var wire 1 $ b_psel $end
$var wire 1 % b_pready $end
$var wire 6 u b_prdata [5:0] $end
$var wire 8 v b_paddr [7:0] $end
$var parameter 32 w ADDR_WD $end
$var parameter 32 x DATA_WD $end
$var parameter 32 y PROT_WD $end
$var parameter 32 z STRB_WD $end
$var reg 8 { b_paddr_r [7:0] $end
$var reg 1 | b_penable_r $end
$var reg 4 } b_pprot_r [3:0] $end
$var reg 1 $ b_psel_r $end
$var reg 2 ~ b_pstrb_r [1:0] $end
$var reg 6 !" b_pwdata_r [5:0] $end
$var reg 1 "" b_pwrite_r $end
$var reg 1 #" b_ready_req_r $end
$var reg 1 $" q1_r $end
$var reg 1 %" q2_r $end
$var reg 1 &" q3_r $end
$var reg 6 '" rdata_r [5:0] $end
$upscope $end
$upscope $end
$scope module slave_mux $end
$var wire 8 (" b_paddr [7:0] $end
$var wire 1 9 b_pclk $end
$var wire 1 ( b_penable $end
$var wire 4 )" b_pprot [3:0] $end
$var wire 6 *" b_prdata [5:0] $end
$var wire 1 % b_pready $end
$var wire 1 : b_prst_n $end
$var wire 1 $ b_psel $end
$var wire 2 +" b_pstrb [1:0] $end
$var wire 6 ," b_pwdata [5:0] $end
$var wire 1 ! b_pwrite $end
$var wire 1 -" pready0 $end
$var wire 1 ." pready1 $end
$var wire 1 /" pready2 $end
$var wire 1 0" pready3 $end
$var wire 1 1" psel0 $end
$var wire 1 2" psel1 $end
$var wire 1 3" psel2 $end
$var wire 1 4" psel3 $end
$var wire 4 5" selx [3:0] $end
$var wire 6 6" prdata3 [5:0] $end
$var wire 6 7" prdata2 [5:0] $end
$var wire 6 8" prdata1 [5:0] $end
$var wire 6 9" prdata0 [5:0] $end
$var wire 2 :" addrx [1:0] $end
$var parameter 32 ;" ADDR_WD $end
$var parameter 32 <" DATA_WD $end
$var parameter 32 =" PROT_WD $end
$var parameter 32 >" STRB_WD $end
$var reg 6 ?" b_prdata_r [5:0] $end
$scope module slave0 $end
$var wire 8 @" b_paddr [7:0] $end
$var wire 1 9 b_pclk $end
$var wire 1 ( b_penable $end
$var wire 4 A" b_pprot [3:0] $end
$var wire 6 B" b_prdata [5:0] $end
$var wire 1 -" b_pready $end
$var wire 1 : b_prst_n $end
$var wire 1 1" b_psel $end
$var wire 2 C" b_pstrb [1:0] $end
$var wire 6 D" b_pwdata [5:0] $end
$var wire 1 ! b_pwrite $end
$var wire 6 E" b_paddr_L [5:0] $end
$var parameter 32 F" ADDR_WD $end
$var parameter 33 G" ADDR_WD_L $end
$var parameter 32 H" DATA_WD $end
$var parameter 32 I" PROT_WD $end
$var parameter 32 J" STRB_WD $end
$upscope $end
$scope module slave1 $end
$var wire 8 K" b_paddr [7:0] $end
$var wire 1 9 b_pclk $end
$var wire 1 ( b_penable $end
$var wire 4 L" b_pprot [3:0] $end
$var wire 6 M" b_prdata [5:0] $end
$var wire 1 ." b_pready $end
$var wire 1 : b_prst_n $end
$var wire 1 2" b_psel $end
$var wire 2 N" b_pstrb [1:0] $end
$var wire 6 O" b_pwdata [5:0] $end
$var wire 1 ! b_pwrite $end
$var wire 6 P" b_paddr_L [5:0] $end
$var parameter 32 Q" ADDR_WD $end
$var parameter 33 R" ADDR_WD_L $end
$var parameter 32 S" DATA_WD $end
$var parameter 32 T" PROT_WD $end
$var parameter 32 U" STRB_WD $end
$upscope $end
$scope module slave2 $end
$var wire 8 V" b_paddr [7:0] $end
$var wire 1 9 b_pclk $end
$var wire 1 ( b_penable $end
$var wire 4 W" b_pprot [3:0] $end
$var wire 6 X" b_prdata [5:0] $end
$var wire 1 /" b_pready $end
$var wire 1 : b_prst_n $end
$var wire 1 3" b_psel $end
$var wire 2 Y" b_pstrb [1:0] $end
$var wire 6 Z" b_pwdata [5:0] $end
$var wire 1 ! b_pwrite $end
$var wire 6 [" b_paddr_L [5:0] $end
$var parameter 32 \" ADDR_WD $end
$var parameter 33 ]" ADDR_WD_L $end
$var parameter 32 ^" DATA_WD $end
$var parameter 32 _" PROT_WD $end
$var parameter 32 `" STRB_WD $end
$upscope $end
$scope module slave3 $end
$var wire 8 a" b_paddr [7:0] $end
$var wire 1 9 b_pclk $end
$var wire 1 ( b_penable $end
$var wire 4 b" b_pprot [3:0] $end
$var wire 6 c" b_prdata [5:0] $end
$var wire 1 0" b_pready $end
$var wire 1 : b_prst_n $end
$var wire 1 4" b_psel $end
$var wire 2 d" b_pstrb [1:0] $end
$var wire 6 e" b_pwdata [5:0] $end
$var wire 1 ! b_pwrite $end
$var wire 6 f" b_paddr_L [5:0] $end
$var parameter 32 g" ADDR_WD $end
$var parameter 33 h" ADDR_WD_L $end
$var parameter 32 i" DATA_WD $end
$var parameter 32 j" PROT_WD $end
$var parameter 32 k" STRB_WD $end
$upscope $end
$upscope $end
$upscope $end
$enddefinitions $end
$comment Show the parameter values. $end
$dumpall
b10 k"
b100 j"
b110 i"
b110 h"
b1000 g"
b10 `"
b100 _"
b110 ^"
b110 ]"
b1000 \"
b10 U"
b100 T"
b110 S"
b110 R"
b1000 Q"
b10 J"
b100 I"
b110 H"
b110 G"
b1000 F"
b10 >"
b100 ="
b110 <"
b1000 ;"
b10 z
b100 y
b110 x
b1000 w
b10 `
b100 _
b110 ^
b1000 ]
b10 Q
b100 P
b110 O
b1000 N
b10 /
b100 .
b110 -
b1000 ,
$end
#0
$dumpvars
bx f"
bx e"
bx d"
bx c"
bx b"
bx a"
bx ["
bx Z"
bx Y"
bx X"
bx W"
bx V"
bx P"
bx O"
bx N"
bx M"
bx L"
bx K"
bx E"
bx D"
bx C"
bx B"
bx A"
bx @"
bx ?"
bx :"
bx 9"
bx 8"
bx 7"
bx 6"
bx 5"
x4"
x3"
x2"
x1"
10"
1/"
1."
1-"
bx ,"
bx +"
bx *"
bx )"
bx ("
bx '"
x&"
x%"
x$"
x#"
x""
bx !"
bx ~
bx }
x|
bx {
bx v
bx u
bx t
b11 s
bx r
bx q
bx p
bx o
bx n
bx m
xl
xk
xj
xi
xh
bx g
bx f
xe
bx d
bx c
bx b
xa
bx \
bx [
b11 Z
bx Y
xX
bx W
bx V
b11 U
bx T
b0 S
bx R
xM
bx L
bx K
bx J
bx I
bx H
bx G
bx F
xE
bx D
bx C
b11 B
bx A
x@
bx ?
b11 >
b0 =
bx <
bx ;
1:
09
x8
bx 7
b11 6
x5
14
b0 3
x2
01
bx 0
bx +
x*
bx )
x(
bx '
bx &
x%
x$
bx #
bx "
x!
$end
#1
0l
01"
02"
03"
04"
0X
0$"
0%"
0&"
0$
0E
0#"
0(
0|
0i
0j
0k
0M
0a
1*
1e
05
02
b0 ;
18
0:
04
#2
1:
14
#3
b0 7
b0 ?
b0 V
b0 0
b0 <
b0 R
11
#6
01
19
#9
15
11
#12
01
09
#15
12
0*
0e
b11 f
b0 D
b0 Y
b0 q
b0 c
b0 K
b0 W
b0 m
b0 b
b0 A
b0 [
b0 t
b0 g
1@
1h
1M
1a
11
#18
1$"
01
19
#21
11
#24
01
09
#27
11
#30
1l
1%"
01
19
#33
11
#36
01
09
#39
11
#42
1%
0l
11"
02"
03"
04"
b1 5"
b0 :"
b0 E"
b0 P"
b0 ["
b0 f"
1&"
1$
b11 #
b11 G
b11 o
b11 +"
b11 C"
b11 N"
b11 Y"
b11 d"
b11 ~
b0 '
b0 I
b0 n
b0 )"
b0 A"
b0 L"
b0 W"
b0 b"
b0 }
b0 )
b0 J
b0 v
b0 {
b0 ("
b0 @"
b0 K"
b0 V"
b0 a"
b0 "
b0 F
b0 p
b0 ,"
b0 D"
b0 O"
b0 Z"
b0 e"
b0 !"
1!
1""
01
19
#45
11
#48
01
09
#51
11
#54
1(
1|
01
19
#57
11
#60
01
09
#63
11
#66
01"
b0 &
b0 H
b0 u
b0 *"
b0 ?"
0$
1E
1#"
0(
0|
b0 9"
b0 B"
b0 8"
b0 M"
b0 7"
b0 X"
b0 6"
b0 c"
01
19
#69
1i
11
#72
01
09
#75
1X
1j
11
#78
01
19
#81
0X
1k
1*
1e
11
#84
01
09
#87
b1 ;
02
11
#90
01
19
#93
0M
0a
0*
0e
12
b1 7
b1 ?
b1 V
b1 0
b1 <
b1 R
11
#96
01
09
#99
11
#102
0$"
01
19
#105
11
#108
01
09
#111
11
#114
1l
0%"
01
19
#117
11
#120
01
09
#123
11
#126
11"
0l
1$
0&"
01
19
#129
11
#132
01
09
#135
11
#138
1(
1|
01
19
#141
11
#144
01
09
#147
11
#150
01"
0E
0#"
0(
0|
0$
01
19
#153
0i
11
#156
01
09
#159
1X
0j
11
#162
01
19
#165
0X
0k
1*
1e
11
#168
01
09
#171
b10 ;
02
11
#174
01
19
#177
b1 K
b1 W
b1 m
b1 b
b1 A
b1 [
b1 t
b1 g
1M
1a
0*
0e
12
b10 7
b10 ?
b10 V
b10 0
b10 <
b10 R
11
#180
01
09
#183
11
#186
1$"
01
19
#189
11
#192
01
09
#195
11
#198
1l
1%"
01
19
#201
11
#204
01
09
#207
11
